pykatsuyou/__init__.py
pykatsuyou/cli.py
pykatsuyou/dataframes.py
pykatsuyou/exceptions.py
pykatsuyou/godan.py
pykatsuyou/iAdj.py
pykatsuyou/ichidan.py
pykatsuyou/irregulars.py
pykatsuyou/naAdj.py
pykatsuyou/pykatsuyou.py
PyKatsuyou-1.1.1.dist-info/LICENSE
PyKatsuyou-1.1.1.dist-info/METADATA
PyKatsuyou-1.1.1.dist-info/WHEEL
PyKatsuyou-1.1.1.dist-info/entry_points.txt
PyKatsuyou-1.1.1.dist-info/top_level.txt
PyKatsuyou-1.1.1.dist-info/RECORD
