Metadata-Version: 2.1
Name: PyKatsuyou
Version: 1.1.1
Summary: A Japanese inflections tool
Home-page: https://github.com/SmashinFries/PyKatsuyou
Author: Justin Lukasik
Author-email: jus10luka@gmail.com
Maintainer: Smashinfries
Project-URL: Bug Tracker, https://github.com/SmashinFries/PyKatsuyou/issues
Keywords: japanese,inflections,conjugation
Classifier: Programming Language :: Python :: 3
Classifier: License :: OSI Approved :: MIT License
Classifier: Operating System :: OS Independent
Classifier: Intended Audience :: Developers
Classifier: Intended Audience :: Education
Classifier: Natural Language :: Japanese
Classifier: Topic :: Text Processing :: Linguistic
Requires-Python: >=3.6
License-File: LICENSE
Requires-Dist: pandas
Requires-Dist: igo-python
Requires-Dist: jaconv
Requires-Dist: tabulate
